pythontiles/__init__.py
pythontiles/board.py
pythontiles/nmedecode.py
pythontiles/parse.py
pythontiles-1.0.5.dist-info/licenses/LICENSE
pythontiles-1.0.5.dist-info/WHEEL
pythontiles-1.0.5.dist-info/METADATA
pythontiles-1.0.5.dist-info/RECORD
