Metadata-Version: 2.4
Name: pythontiles
Version: 1.0.5
Summary: Framework for tile-based games like chess
Author-email: Chris Knowlson <22knowlson@parmiters.herts.sch.uk>
License-Expression: MIT
License-File: LICENSE
Project-URL: Home, https://github.com/JammingJammerIsJammingToJam/pythontiles
